PyValentina-0.2.0.dist-info/DESCRIPTION.rst
PyValentina-0.2.0.dist-info/METADATA
PyValentina-0.2.0.dist-info/RECORD
PyValentina-0.2.0.dist-info/WHEEL
PyValentina-0.2.0.dist-info/metadata.json
PyValentina-0.2.0.dist-info/top_level.txt
Valentina/__init__.py
Valentina/FileFormat/Measurements.py
Valentina/FileFormat/Pattern.py
Valentina/FileFormat/__init__.py
Valentina/Geometry/Bezier.py
Valentina/Geometry/Conic.py
Valentina/Geometry/Line.py
Valentina/Geometry/Primitive.py
Valentina/Geometry/Segment.py
Valentina/Geometry/Transformation.py
Valentina/Geometry/Vector.py
Valentina/Geometry/__init__.py
Valentina/Graph/DirectedAcyclicGraph.py
Valentina/Graph/__init__.py
Valentina/GraphicScene/GraphicItem.py
Valentina/GraphicScene/Scene.py
Valentina/GraphicScene/__init__.py
Valentina/Logging/Basic.py
Valentina/Logging/__init__.py
Valentina/Math/Functions.py
Valentina/Math/__init__.py
Valentina/Painter/Painter.py
Valentina/Painter/Paper.py
Valentina/Painter/TexPainter.py
Valentina/Painter/__init__.py
Valentina/Pattern/Calculation.py
Valentina/Pattern/Calculator.py
Valentina/Pattern/Contour.py
Valentina/Pattern/Measurement.py
Valentina/Pattern/Pattern.py
Valentina/Pattern/__init__.py
Valentina/TeX/Buffer.py
Valentina/TeX/Document.py
Valentina/TeX/Environment.py
Valentina/TeX/Tikz.py
Valentina/TeX/__init__.py
Valentina/Tools/IterTools.py
Valentina/Tools/__init__.py
Valentina/Xml/Objectivity.py
Valentina/Xml/XmlFile.py
Valentina/Xml/__init__.py
