Metadata-Version: 2.0
Name: PyValentina
Version: 0.2.0
Summary: Python implementation of Valentina Pattern Making Software
Home-page: https://github.com/FabriceSalvaire/PyValentina
Author: Fabrice Salvaire
Author-email: fabrice.salvaire@orange.fr
License: GPLv3
Keywords: pattern making valentina
Platform: any
Classifier: Topic :: Scientific/Engineering
Classifier: Intended Audience :: Education
Classifier: Development Status :: 5 - Production/Stable
Classifier: License :: OSI Approved :: GNU General Public License v3 (GPLv3)
Classifier: Operating System :: OS Independent
Classifier: Programming Language :: Python :: 3.5
Requires-Dist: IntervalArithmetic
Requires-Dist: astunparse
Requires-Dist: lxml
Requires-Dist: numpy
